t90_package/__init__.py
t90_package/main_code.py
t90_package-0.1.0.dist-info/METADATA
t90_package-0.1.0.dist-info/WHEEL
t90_package-0.1.0.dist-info/top_level.txt
t90_package-0.1.0.dist-info/RECORD
