Metadata-Version: 2.4
Name: t90_package
Version: 0.1.0
Summary: This package guesses a number
Author-email: Hamza <ameer.hamza@siparadigm.com>
License: MIT
Requires-Python: >=3.7
